pyzdcf/__init__.py
pyzdcf/pyzdcf.py
pyzdcf-1.0.3.dist-info/LICENSE
pyzdcf-1.0.3.dist-info/METADATA
pyzdcf-1.0.3.dist-info/WHEEL
pyzdcf-1.0.3.dist-info/RECORD
