Metadata-Version: 2.3
Name: pyzdcf
Version: 1.0.3
Summary: Python module used for robust estimation of cross-corelation functions of sparse and unevenly sampled astronomical time-series. It emulates a Fortran program called ZDCF which is based on the Z-transformed Discrete Correlation Function algorithm (ZDCF, Alexander 1997).
License: MIT
Author: Isidora Jankov
Author-email: ijankov@proton.me
Requires-Python: >=3.9,<3.14
Classifier: Intended Audience :: Science/Research
Classifier: License :: OSI Approved :: MIT License
Classifier: Programming Language :: Python :: 3
Classifier: Programming Language :: Python :: 3.9
Classifier: Programming Language :: Python :: 3.10
Classifier: Programming Language :: Python :: 3.11
Classifier: Programming Language :: Python :: 3.12
Classifier: Programming Language :: Python :: 3.13
Classifier: Topic :: Scientific/Engineering :: Astronomy
Requires-Dist: numpy (>=1.21.6,<2.0.0)
Requires-Dist: pandas (>=2.2.3,<3.0.0)
Requires-Dist: scipy (>=1.11,<2.0)
Project-URL: Repository, https://github.com/LSST-sersag/pyzdcf
